Collector/Collector.py
Collector/__init__.py
Collector/__main__.py
CovReporter/CovReporter.py
CovReporter/__init__.py
CovReporter/__main__.py
EC2Reporter/EC2Reporter.py
EC2Reporter/__init__.py
EC2Reporter/__main__.py
FTB/AssertionHelper.py
FTB/ConfigurationFiles.py
FTB/CoverageHelper.py
FTB/ProgramConfiguration.py
FTB/__init__.py
FTB/Running/AutoRunner.py
FTB/Running/GDB.py
FTB/Running/PersistentApplication.py
FTB/Running/StreamCollector.py
FTB/Running/WaitpidMonitor.py
FTB/Running/__init__.py
FTB/Signatures/CrashInfo.py
FTB/Signatures/CrashSignature.py
FTB/Signatures/JSONHelper.py
FTB/Signatures/Matchers.py
FTB/Signatures/RegisterHelper.py
FTB/Signatures/Symptom.py
FTB/Signatures/__init__.py
Reporter/Reporter.py
Reporter/__init__.py
TaskStatusReporter/TaskStatusReporter.py
TaskStatusReporter/__init__.py
TaskStatusReporter/__main__.py
fuzzmanager-0.9.1.dist-info/licenses/LICENSE
fuzzmanager-0.9.1.dist-info/METADATA
fuzzmanager-0.9.1.dist-info/WHEEL
fuzzmanager-0.9.1.dist-info/entry_points.txt
fuzzmanager-0.9.1.dist-info/top_level.txt
fuzzmanager-0.9.1.dist-info/RECORD
