Metadata-Version: 2.4
Name: FuzzManager
Version: 0.9.1
Summary: A fuzzing management tools collection
Home-page: https://github.com/MozillaSecurity/FuzzManager
Author: Christian Holler
Maintainer: Mozilla Fuzzing Team
Maintainer-email: fuzzing@mozilla.com
License: MPL 2.0
Keywords: fuzz fuzzing security test testing
Classifier: Intended Audience :: Developers
Classifier: License :: OSI Approved :: Mozilla Public License 2.0 (MPL 2.0)
Classifier: Operating System :: OS Independent
Classifier: Programming Language :: Python
Classifier: Programming Language :: Python :: 3
Classifier: Topic :: Software Development :: Testing
Classifier: Topic :: Security
Requires-Python: >=3.9
License-File: LICENSE
Requires-Dist: fasteners>=0.14.1
Requires-Dist: requests>=2.20.1
Dynamic: license-file
